nikassets/__init__.py
nikassets/helper/Assets.py
nikassets/helper/__init__.py
nikassets/helper/assets/NikGappsZipSigner.jar
nikassets/helper/assets/apksigner.jar
nikassets/helper/assets/apktool_2.10.0.jar
nikassets/helper/assets/apktool_2.11.1.jar
nikassets/helper/assets/busybox
nikassets/helper/assets/cert.pk8
nikassets/helper/assets/cert.x509.pem
nikassets/helper/assets/gofile.sh
nikassets/helper/assets/private_key.pem
nikassets/helper/assets/update-binary-busybox
nikassets/helper/assets/bin/Darwin/aapt2
nikassets/helper/assets/bin/Linux/aapt2
nikassets/helper/assets/bin/Linux/dex-tools-2.2-SNAPSHOT-2021-10-31.zip
nikassets/helper/assets/bin/Linux/jd-gui-1.6.6-min.jar
nikassets/helper/assets/bin/Windows/AdbWinApi.dll
nikassets/helper/assets/bin/Windows/AdbWinUsbApi.dll
nikassets/helper/assets/bin/Windows/aapt.exe
nikassets/helper/assets/bin/Windows/aapt2.exe
nikassets/helper/assets/bin/Windows/aapt_64.exe
nikassets/helper/assets/bin/Windows/adb.exe
nikassets-0.13.dist-info/METADATA
nikassets-0.13.dist-info/WHEEL
nikassets-0.13.dist-info/entry_points.txt
nikassets-0.13.dist-info/top_level.txt
nikassets-0.13.dist-info/RECORD
