Metadata-Version: 2.4
Name: nikassets
Version: 0.13
Summary: A short description of your project
Home-page: https://github.com/nikhilmenghani/nikassets
Author: Nikhil Menghani
Author-email: nikhil@menghani.com
Classifier: Programming Language :: Python :: 3
Classifier: License :: OSI Approved :: MIT License
Requires-Python: >=3.12
Requires-Dist: setuptools>=75.1.0
Dynamic: author
Dynamic: author-email
Dynamic: classifier
Dynamic: description
Dynamic: description-content-type
Dynamic: home-page
Dynamic: requires-dist
Dynamic: requires-python
Dynamic: summary
